slacksocket/__init__.py
slacksocket/client.py
slacksocket/config.py
slacksocket/errors.py
slacksocket/models.py
slacksocket/version.py
slacksocket/webclient.py
slacksocket-1.0.1.dist-info/LICENSE
slacksocket-1.0.1.dist-info/METADATA
slacksocket-1.0.1.dist-info/WHEEL
slacksocket-1.0.1.dist-info/top_level.txt
slacksocket-1.0.1.dist-info/RECORD
