Metadata-Version: 2.1
Name: slacksocket
Version: 1.0.1
Summary: Slack RTM API Websocket client
Home-page: https://github.com/vektorlab/slacksocket
Author: Bradley Cicenas
Author-email: bradley@vektor.nyc
License: http://opensource.org/licenses/MIT
Keywords: slack rtm websocket chat api
Platform: UNKNOWN
Classifier: Intended Audience :: Developers
Classifier: License :: OSI Approved :: MIT License 
Classifier: Natural Language :: English
Classifier: Programming Language :: Python
Classifier: Programming Language :: Python :: 2
Classifier: Programming Language :: Python :: 3
Requires-Dist: requests (>=2.9.1)
Requires-Dist: websocket-client (==0.56.0)
